list/__init__.py
list/count.py
list/for_each.py
list/read.py
list/write.py
list/strutils/__init__.py
list/strutils/to_list.py
list/strutils/to_str.py
devkit_list-2024.2.1.1.post1.dist-info/METADATA
devkit_list-2024.2.1.1.post1.dist-info/WHEEL
devkit_list-2024.2.1.1.post1.dist-info/top_level.txt
devkit_list-2024.2.1.1.post1.dist-info/RECORD
