Metadata-Version: 2.1
Name: devkit-list
Version: 2024.2.1.1.post1
Summary: Some useful list tools. 
Author: Pemrilect
Author-email: 49397056@qq.com
License: MIT
